iso15118/__init__.py
iso15118/evcc/__init__.py
iso15118/evcc/comm_session_handler.py
iso15118/evcc/controller/__init__.py
iso15118/evcc/controller/interface.py
iso15118/evcc/controller/simulator.py
iso15118/evcc/evcc_config.py
iso15118/evcc/evcc_settings.py
iso15118/evcc/main.py
iso15118/evcc/states/__init__.py
iso15118/evcc/states/din_spec_states.py
iso15118/evcc/states/evcc_state.py
iso15118/evcc/states/iso15118_20_states.py
iso15118/evcc/states/iso15118_2_states.py
iso15118/evcc/states/sap_states.py
iso15118/evcc/transport/__init__.py
iso15118/evcc/transport/tcp_client.py
iso15118/evcc/transport/udp_client.py
iso15118/py.typed
iso15118/secc/__init__.py
iso15118/secc/comm_session_handler.py
iso15118/secc/controller/__init__.py
iso15118/secc/controller/common.py
iso15118/secc/controller/ev_data.py
iso15118/secc/controller/evse_data.py
iso15118/secc/controller/interface.py
iso15118/secc/controller/simulator.py
iso15118/secc/failed_responses.py
iso15118/secc/main.py
iso15118/secc/secc_settings.py
iso15118/secc/states/__init__.py
iso15118/secc/states/din_spec_states.py
iso15118/secc/states/iso15118_20_states.py
iso15118/secc/states/iso15118_2_states.py
iso15118/secc/states/sap_states.py
iso15118/secc/states/secc_state.py
iso15118/secc/transport/__init__.py
iso15118/secc/transport/tcp_server.py
iso15118/secc/transport/udp_server.py
iso15118/shared/EXICodec.jar
iso15118/shared/__init__.py
iso15118/shared/comm_session.py
iso15118/shared/examples/evcc/DIN/evcc_config.json
iso15118/shared/examples/evcc/iso15118_2/evcc_config_eim_ac.json
iso15118/shared/examples/evcc/iso15118_2/evcc_config_eim_dc.json
iso15118/shared/examples/evcc/iso15118_2/evcc_config_pnc_ac.json
iso15118/shared/examples/evcc/iso15118_2/evcc_config_pnc_dc.json
iso15118/shared/examples/evcc/iso15118_20/evcc_config_ac.json
iso15118/shared/examples/evcc/iso15118_20/evcc_config_ac_bpt.json
iso15118/shared/examples/evcc/iso15118_20/evcc_config_dc.json
iso15118-0.31.2.dist-info/METADATA
iso15118-0.31.2.dist-info/WHEEL
iso15118-0.31.2.dist-info/entry_points.txt
iso15118-0.31.2.dist-info/licenses/LICENSE
iso15118-0.31.2.dist-info/RECORD
