Metadata-Version: 2.4
Name: iso15118
Version: 0.31.2
Summary: Implementation of DIN SPEC 70121, ISO 15118-2 and -20 specs for SECC
License-File: LICENSE
Author: André Duarte
Author-email: andre@ecog.io
Requires-Python: >=3.9, !=2.7.*, !=3.0.*, !=3.1.*, !=3.2.*, !=3.3.*, !=3.4.*, !=3.5.*, !=3.6.*, !=3.7.*, !=3.8.*
Classifier: Programming Language :: Python :: 3
Classifier: Programming Language :: Python :: 3.10
Classifier: Programming Language :: Python :: 3.11
Classifier: Programming Language :: Python :: 3.12
Classifier: Programming Language :: Python :: 3.13
Classifier: Programming Language :: Python :: 3.14
Requires-Dist: cryptography (==44.0.0)
Requires-Dist: environs (>=14.1.0,<15.0.0)
Requires-Dist: mypy-extensions (>=1.0.0,<2.0.0)
Requires-Dist: psutil (>=6.1.1,<7.0.0)
Requires-Dist: py4j (>=0.10.9,<0.11.0)
Requires-Dist: pydantic (==1.10.21)
Requires-Dist: types-psutil (>=6.1.0.20241221,<7.0.0.0)
Requires-Dist: types-toml (>=0.10.8.7,<0.11.0.0)
